web_research_graph/__init__.py
web_research_graph/configuration.py
web_research_graph/graph.py
web_research_graph/prompts.py
web_research_graph/state.py
web_research_graph/tools.py
web_research_graph/utils.py
web_research_graph/interviews_graph/__init__.py
web_research_graph/interviews_graph/graph.py
web_research_graph/interviews_graph/router.py
web_research_graph/interviews_graph/answers_graph/__init__.py
web_research_graph/interviews_graph/answers_graph/graph.py
web_research_graph/interviews_graph/answers_graph/nodes/__init__.py
web_research_graph/interviews_graph/answers_graph/nodes/generate.py
web_research_graph/interviews_graph/answers_graph/nodes/search.py
web_research_graph/interviews_graph/nodes/__init__.py
web_research_graph/interviews_graph/nodes/initialize.py
web_research_graph/interviews_graph/nodes/next_editor.py
web_research_graph/interviews_graph/nodes/question.py
web_research_graph/nodes/__init__.py
web_research_graph/nodes/article_generator.py
web_research_graph/nodes/outline_generator.py
web_research_graph/nodes/outline_refiner.py
web_research_graph/nodes/perspectives_generator.py
web_research_graph/nodes/topic_expander.py
web_research_graph/nodes/topic_input.py
web_research_graph/nodes/topic_validator.py
web_research_graph-0.0.5.dist-info/LICENSE
web_research_graph-0.0.5.dist-info/METADATA
web_research_graph-0.0.5.dist-info/WHEEL
web_research_graph-0.0.5.dist-info/top_level.txt
web_research_graph-0.0.5.dist-info/RECORD
